LICENSE.txt
README.md
setup.cfg
setup.py
pykuma/__init__.py
pykuma/helper.py
pykuma/setup.py
pykuma.egg-info/PKG-INFO
pykuma.egg-info/SOURCES.txt
pykuma.egg-info/dependency_links.txt
pykuma.egg-info/requires.txt
pykuma.egg-info/top_level.txt